[
  { "month": "2025/03", "cost": "18317", "date": "2025/3/8" },
  { "month": "2025/02", "cost": "17719", "date": "2025/2/8" },
  { "month": "2025/01", "cost": "14010", "date": "2025/1/18" },
  { "month": "2024/12", "cost": "10420", "date": "2024/12/10" },
  { "month": "2024/11", "cost": "8382", "date": "2024/11/9" },
  { "month": "2024/10", "cost": "13793", "date": "2024/10/9" },
  { "month": "2024/09", "cost": "15750", "date": "2024/9/9" },
  { "month": "2024/08", "cost": "12137", "date": "2024/8/9" },
  { "month": "2024/07", "cost": "7490", "date": "2024/7/6" },
  { "month": "2024/06", "cost": "8029", "date": "2024/6/9" },
  { "month": "2024/05", "cost": "8708", "date": "2024/5/10" },
  { "month": "2024/04", "cost": "11685", "date": "2024/4/7" },
  { "month": "2024/03", "cost": "13049", "date": "2024/4/7" },
  { "month": "2024/02", "cost": "13506", "date": "2024/3/10" },
  { "month": "2024/01", "cost": "10224", "date": "2024/2/8" },
  { "month": "2023/12", "cost": "8367", "date": "2024/1/12" },
  { "month": "2023/11", "cost": "7293", "date": "2023/12/9" },
  { "month": "2023/10", "cost": "9816", "date": "2023/11/11" },
  { "month": "2023/09", "cost": "11477", "date": "2023/10/8" },
  { "month": "2023/08", "cost": "11751", "date": "2023/9/9" },
  { "month": "2023/07", "cost": "7139", "date": "2023/8/12" },
  { "month": "2023/06", "cost": "5980", "date": "2023/7/17" },
  { "month": "2023/05", "cost": "7537", "date": "2023/6/9" },
  { "month": "2023/04", "cost": "8119", "date": "2023/5/11" },
  { "month": "2023/03", "cost": "12141", "date": "2023/4/15" },
  { "month": "2023/02", "cost": "13688", "date": "2023/3/9" },
  { "month": "2023/01", "cost": "11150", "date": "2023/2/9" },
  { "month": "2022/12", "cost": "9619", "date": "N/A" },
  { "month": "2022/11", "cost": "8615", "date": "N/A" },
  { "month": "2022/10", "cost": "11954", "date": "N/A" },
  { "month": "2022/09", "cost": "13693", "date": "N/A" },
  { "month": "2022/08", "cost": "11466", "date": "N/A" }
]
